LICENSE
MANIFEST.in
README.md
setup.cfg
setup.py
ads_txt/__init__.py
ads_txt/admin.py
ads_txt/apps.py
ads_txt/models.py
ads_txt/settings.py
ads_txt/urls.py
ads_txt/views.py
ads_txt/migrations/0001_initial.py
ads_txt/migrations/__init__.py
ads_txt/templates/ads_txt/rule_list.html
django_ads_txt.egg-info/PKG-INFO
django_ads_txt.egg-info/SOURCES.txt
django_ads_txt.egg-info/dependency_links.txt
django_ads_txt.egg-info/top_level.txt